tj_text/__init__.py
tj_text/tj_preproc.py
tj_preproc-0.0.3.dist-info/LICENSE
tj_preproc-0.0.3.dist-info/METADATA
tj_preproc-0.0.3.dist-info/WHEEL
tj_preproc-0.0.3.dist-info/top_level.txt
tj_preproc-0.0.3.dist-info/RECORD
