Metadata-Version: 2.1
Name: tj-preproc
Version: 0.0.3
Summary: An NLP Text Preprocessing Package
Home-page: https://github.com/pypi_projects/tj_nlp/
Author: Tariq Jamil
Author-email: tariqjamil.bwp@gmail.com
License: MIT
Project-URL: Bug Tracker, https://github.com/tariqjamil-bwp/pypi_projects/issues
Project-URL: repository, https://github.com/tariqjamil-bwp/pypi_projects/tree/main/tj_nlp
Keywords: tjtext_preproc_ds
Classifier: Programming Language :: Python :: 3
Classifier: License :: OSI Approved :: MIT License
Classifier: Operating System :: OS Independent
Requires-Python: >=3.6
License-File: LICENSE
Requires-Dist: unidecode
Requires-Dist: nltk
Requires-Dist: autocorrect
Requires-Dist: bs4
Requires-Dist: pandas
Requires-Dist: numpy
Requires-Dist: tqdm
